setup.cfg
setup.py
django_maintenance/__init__.py
django_maintenance/maintenance.py
django_maintenance/maintenance_settings.json
django_maintenance/tests.py
django_maintenance/management/__init__.py
django_maintenance/management/commands/__init__.py
django_maintenance/management/commands/maintenance.py
django_maintenance/templates/django_maintenance/maintenance.html
django_under_maintenance.egg-info/PKG-INFO
django_under_maintenance.egg-info/SOURCES.txt
django_under_maintenance.egg-info/dependency_links.txt
django_under_maintenance.egg-info/top_level.txt