Metadata-Version: 1.1
Name: django-under-maintenance
Version: 0.1
Summary: Setting you site Under Maintenance.
Home-page: UNKNOWN
Author: Ricardo Castro
Author-email: mcc.ricardo@gmail.com
License: UNKNOWN
Download-URL: https://github.com/mccricardo/django_maintenance
Keywords: django,maintenance
Platform: UNKNOWN
